django_ninja_keycloak/__init__.py
django_ninja_keycloak/keycloak.py
django_ninja_keycloak/keycloak_basic_auth.py
django_ninja_keycloak/keycloak_http_bearer.py
django_ninja_keycloak-0.0.5.dist-info/LICENSE
django_ninja_keycloak-0.0.5.dist-info/METADATA
django_ninja_keycloak-0.0.5.dist-info/WHEEL
django_ninja_keycloak-0.0.5.dist-info/top_level.txt
django_ninja_keycloak-0.0.5.dist-info/RECORD
