Metadata-Version: 2.1
Name: django-ninja-keycloak
Version: 0.0.5
Summary: Django Ninja package to integrate keycloak authentication
Home-page: UNKNOWN
Author: kgaulin (Kevin Gaulin)
License: UNKNOWN
Keywords: python,django-ninja,keycloak
Platform: UNKNOWN
Classifier: Development Status :: 2 - Pre-Alpha
Classifier: Intended Audience :: Developers
Classifier: Programming Language :: Python :: 3
Classifier: Operating System :: Unix
Classifier: Operating System :: MacOS :: MacOS X
Classifier: Operating System :: Microsoft :: Windows
License-File: LICENSE
Requires-Dist: python-keycloak
Requires-Dist: django-ninja
Requires-Dist: pyjwt
